COPYING
MANIFEST.in
README.rst
bootstrap.py
buildout.cfg
setup.py
config/database/nist_sre12/female.py
config/database/nist_sre12/male.py
config/features/lfcc_60.py
config/features/mfcc_60.py
config/grid/demanding.py
config/grid/grid.py
config/grid/para_ivector_training.py
config/grid/very_demanding.py
config/preprocessing/energy.py
config/preprocessing/external.py
config/preprocessing/mod_4hz.py
config/tools/isv/isv_256g_u50.py
config/tools/isv/isv_512g_u200.py
config/tools/isv/isv_512g_u50.py
config/tools/isv/isv_8g_u20.py
config/tools/ivec/ivec_256g_t100_cosine.py
config/tools/ivec/ivec_256g_t100_plda.py
config/tools/ivec/ivec_512g_t400.py
config/tools/ivec/ivec_8g_t50.py
config/tools/jfa/jfa_256_v10_u10.py
config/tools/jfa/jfa_256_v5_u10.py
config/tools/jfa/jfa_8_v_5_u_5.py
config/tools/ubm_gmm/ubm_gmm_256G.py
config/tools/ubm_gmm/ubm_gmm_512G.py
config/tools/ubm_gmm/ubm_gmm_512G_regular_scoring.py
config/tools/ubm_gmm/ubm_gmm_8G.py
spear.nist_sre12.egg-info/PKG-INFO
spear.nist_sre12.egg-info/SOURCES.txt
spear.nist_sre12.egg-info/dependency_links.txt
spear.nist_sre12.egg-info/requires.txt
spear.nist_sre12.egg-info/top_level.txt