Metadata-Version: 1.1
Name: spear.nist-sre12
Version: 1.0.0
Summary: Speaker recognition toolchain for NIST SRE 2012
Home-page: http://pypi.python.org/pypi/spear.nist_sre12
Author: Elie Khoury
Author-email: Elie.Khoury@idiap.ch
License: GPLv3
Keywords: bob,xbob,xbob.db,speaker recognition
Platform: UNKNOWN
Classifier: Development Status :: 4 - Beta
Classifier: Intended Audience :: Developers
Classifier: License :: OSI Approved :: GNU General Public License v3 (GPLv3)
Classifier: Natural Language :: English
Classifier: Programming Language :: Python
Classifier: Programming Language :: Python :: 3
Classifier: Topic :: Scientific/Engineering :: Artificial Intelligence
